[
  {"_id":"Seq-0","_barcode":"0001","_name":"Manzanas fuji","_description":"Muy ricas de la china","_price":1.30,"_basePrice":0.3,"_stock":100,"_stockMin":10,"_weighted":true,"_categoryId":"3d8dbdcb-fe7a-4e26-baa4-d74f612fe8d4","_status":"PRODUCT_ENABLED"},
  {"_id":"Seq-1","_barcode":"0002","_name":"Coca-Cola Zero","_description":"","_price":0.6,"_basePrice":0.3,"_stock":1500,"_stockMin":10,"_weighted":false,"_categoryId":"3d8dbdcb-fe7a-4e26-baa4-d74f612fe8d4","_status":"PRODUCT_ENABLED"},
  {"_id":"Seq-2","_barcode":"0003","_name":"Coca-Cola Zero sin cafeina","_description":"","_price":0.6,"_basePrice":0.3,"_stock":1000,"_stockMin":10,"_weighted":false,"_categoryId":"3d8dbdcb-fe7a-4e26-baa4-d74f612fe8d4","_status":"PRODUCT_ENABLED"},
  {"_id":"Seq-3","_barcode":"0004","_name":"Coca-Cola Zero zero","_description":"","_price":0.6,"_basePrice":0.3,"_stock":1000,"_stockMin":10,"_weighted":false,"_categoryId":"3d8dbdcb-fe7a-4e26-baa4-d74f612fe8d4","_status":"PRODUCT_ENABLED"},
  {"_id":"Seq-4","_barcode":"0005","_name":"Coca-Cola Zero 42","_description":"","_price":0.6,"_basePrice":0.3,"_stock":1000,"_stockMin":10,"_weighted":false,"_categoryId":"3d8dbdcb-fe7a-4e26-baa4-d74f612fe8d4","_status":"PRODUCT_ENABLED"},
  {"_id":"Seq-0","_barcode":"0006","_name":"Coca-Cola","_description":"","_price":0.55,"_basePrice":0.3,"_stock":100,"_stockMin":10,"_weighted":false,"_categoryId":"3d8dbdcb-fe7a-4e26-baa4-d74f612fe8d4","_status":"PRODUCT_ENABLED"},
  {"_id":"Seq-1","_barcode":"0007","_name":"Coca-Cola Zero","_description":"","_price":0.6,"_basePrice":0.3,"_stock":1500,"_stockMin":10,"_weighted":false,"_categoryId":"3d8dbdcb-fe7a-4e26-baa4-d74f612fe8d4","_status":"PRODUCT_ENABLED"},
  {"_id":"Seq-2","_barcode":"0008","_name":"Coca-Cola Zero sin cafeina","_description":"","_price":0.6,"_basePrice":0.3,"_stock":1000,"_stockMin":10,"_weighted":false,"_categoryId":"3d8dbdcb-fe7a-4e26-baa4-d74f612fe8d4","_status":"PRODUCT_ENABLED"},
  {"_id":"Seq-3","_barcode":"0009","_name":"Coca-Cola Zero zero","_description":"","_price":0.6,"_basePrice":0.3,"_stock":1000,"_stockMin":10,"_weighted":false,"_categoryId":"3d8dbdcb-fe7a-4e26-baa4-d74f612fe8d4","_status":"PRODUCT_ENABLED"},
  {"_id":"Seq-4","_barcode":"0010","_name":"Coca-Cola Zero 42","_description":"","_price":0.6,"_basePrice":0.3,"_stock":1000,"_stockMin":10,"_weighted":false,"_categoryId":"3d8dbdcb-fe7a-4e26-baa4-d74f612fe8d4","_status":"PRODUCT_ENABLED"},
  {"_id":"Seq-0","_barcode":"0011","_name":"Coca-Cola","_description":"","_price":0.55,"_basePrice":0.3,"_stock":100,"_stockMin":10,"_weighted":false,"_categoryId":"3d8dbdcb-fe7a-4e26-baa4-d74f612fe8d4","_status":"PRODUCT_ENABLED"},
  {"_id":"Seq-1","_barcode":"0012","_name":"Coca-Cola Zero","_description":"","_price":0.6,"_basePrice":0.3,"_stock":1500,"_stockMin":10,"_weighted":false,"_categoryId":"3d8dbdcb-fe7a-4e26-baa4-d74f612fe8d4","_status":"PRODUCT_ENABLED"},
  {"_id":"Seq-2","_barcode":"0013","_name":"Coca-Cola Zero sin cafeina","_description":"","_price":0.6,"_basePrice":0.3,"_stock":10,"_stockMin":100,"_weighted":false,"_categoryId":"3d8dbdcb-fe7a-4e26-baa4-d74f612fe8d4","_status":"PRODUCT_ENABLED"},
  {"_id":"Seq-3","_barcode":"0014","_name":"Coca-Cola Zero zero","_description":"","_price":0.6,"_basePrice":0.3,"_stock":10,"_stockMin":100,"_weighted":false,"_categoryId":"3d8dbdcb-fe7a-4e26-baa4-d74f612fe8d4","_status":"PRODUCT_ENABLED"},
  {"_id":"Seq-4","_barcode":"0015","_name":"Coca-Cola Zero 42","_description":"","_price":0.6,"_basePrice":0.3,"_stock":10,"_stockMin":100,"_weighted":false,"_categoryId":"3d8dbdcb-fe7a-4e26-baa4-d74f612fe8d4","_status":"PRODUCT_ENABLED"},
  {"_id":"Seq-0","_barcode":"0016","_name":"Coca-Cola","_description":"","_price":0.55,"_basePrice":0.3,"_stock":100,"_stockMin":10,"_weighted":false,"_categoryId":"3d8dbdcb-fe7a-4e26-baa4-d74f612fe8d4","_status":"PRODUCT_ENABLED"},
  {"_id":"Seq-1","_barcode":"0017","_name":"Coca-Cola Zero","_description":"","_price":0.6,"_basePrice":0.3,"_stock":1500,"_stockMin":10,"_weighted":false,"_categoryId":"3d8dbdcb-fe7a-4e26-baa4-d74f612fe8d4","_status":"PRODUCT_ENABLED"},
  {"_id":"Seq-2","_barcode":"0018","_name":"Coca-Cola Zero sin cafeina","_description":"","_price":0.6,"_basePrice":0.3,"_stock":10,"_stockMin":100,"_weighted":false,"_categoryId":"3d8dbdcb-fe7a-4e26-baa4-d74f612fe8d4","_status":"PRODUCT_ENABLED"},
  {"_id":"Seq-3","_barcode":"0019","_name":"Coca-Cola Zero zero","_description":"","_price":0.6,"_basePrice":0.3,"_stock":10,"_stockMin":100,"_weighted":false,"_categoryId":"3d8dbdcb-fe7a-4e26-baa4-d74f612fe8d4","_status":"PRODUCT_ENABLED"},
  {"_id":"Seq-4","_barcode":"0020","_name":"Coca-Cola Zero 42","_description":"","_price":0.6,"_basePrice":0.3,"_stock":10,"_stockMin":100,"_weighted":false,"_categoryId":"3d8dbdcb-fe7a-4e26-baa4-d74f612fe8d4","_status":"PRODUCT_ENABLED"},
  {"_id":"Seq-0","_barcode":"0021","_name":"Coca-Cola","_description":"","_price":0.55,"_basePrice":0.3,"_stock":100,"_stockMin":10,"_weighted":false,"_categoryId":"3d8dbdcb-fe7a-4e26-baa4-d74f612fe8d4","_status":"PRODUCT_ENABLED"},
  {"_id":"Seq-1","_barcode":"0022","_name":"Coca-Cola Zero","_description":"","_price":0.6,"_basePrice":0.3,"_stock":1500,"_stockMin":10,"_weighted":false,"_categoryId":"3d8dbdcb-fe7a-4e26-baa4-d74f612fe8d4","_status":"PRODUCT_ENABLED"},
  {"_id":"Seq-2","_barcode":"0023","_name":"Coca-Cola Zero sin cafeina","_description":"","_price":0.6,"_basePrice":0.3,"_stock":10,"_stockMin":100,"_weighted":false,"_categoryId":"3d8dbdcb-fe7a-4e26-baa4-d74f612fe8d4","_status":"PRODUCT_ENABLED"},
  {"_id":"Seq-3","_barcode":"0024","_name":"Coca-Cola Zero zero","_description":"","_price":0.6,"_basePrice":0.3,"_stock":10,"_stockMin":100,"_weighted":false,"_categoryId":"3d8dbdcb-fe7a-4e26-baa4-d74f612fe8d4","_status":"PRODUCT_ENABLED"},
  {"_id":"Seq-4","_barcode":"0025","_name":"Coca-Cola Zero 42","_description":"","_price":0.6,"_basePrice":0.3,"_stock":10,"_stockMin":100,"_weighted":false,"_categoryId":"3d8dbdcb-fe7a-4e26-baa4-d74f612fe8d4","_status":"PRODUCT_ENABLED"},
  {"_id":"Seq-0","_barcode":"0026","_name":"Coca-Cola","_description":"","_price":0.55,"_basePrice":0.3,"_stock":100,"_stockMin":10,"_weighted":false,"_categoryId":"3d8dbdcb-fe7a-4e26-baa4-d74f612fe8d4","_status":"PRODUCT_ENABLED"},
  {"_id":"Seq-1","_barcode":"0027","_name":"Coca-Cola Zero","_description":"","_price":0.6,"_basePrice":0.3,"_stock":1500,"_stockMin":10,"_weighted":false,"_categoryId":"3d8dbdcb-fe7a-4e26-baa4-d74f612fe8d4","_status":"PRODUCT_ENABLED"},
  {"_id":"Seq-2","_barcode":"0028","_name":"Coca-Cola Zero sin cafeina","_description":"","_price":0.6,"_basePrice":0.3,"_stock":10,"_stockMin":100,"_weighted":false,"_categoryId":"3d8dbdcb-fe7a-4e26-baa4-d74f612fe8d4","_status":"PRODUCT_ENABLED"},
  {"_id":"Seq-3","_barcode":"0029","_name":"Coca-Cola Zero zero","_description":"","_price":0.6,"_basePrice":0.3,"_stock":10,"_stockMin":100,"_weighted":false,"_categoryId":"3d8dbdcb-fe7a-4e26-baa4-d74f612fe8d4","_status":"PRODUCT_ENABLED"},
  {"_id":"Seq-4","_barcode":"0030","_name":"Coca-Cola Zero 42","_description":"","_price":0.6,"_basePrice":0.3,"_stock":10,"_stockMin":100,"_weighted":false,"_categoryId":"3d8dbdcb-fe7a-4e26-baa4-d74f612fe8d4","_status":"PRODUCT_ENABLED"},
  {"_id":"Seq-0","_barcode":"0031","_name":"Coca-Cola","_description":"","_price":0.55,"_basePrice":0.3,"_stock":100,"_stockMin":10,"_weighted":false,"_categoryId":"3d8dbdcb-fe7a-4e26-baa4-d74f612fe8d4","_status":"PRODUCT_ENABLED"},
  {"_id":"Seq-1","_barcode":"0032","_name":"Coca-Cola Zero","_description":"","_price":0.6,"_basePrice":0.3,"_stock":1500,"_stockMin":10,"_weighted":false,"_categoryId":"3d8dbdcb-fe7a-4e26-baa4-d74f612fe8d4","_status":"PRODUCT_ENABLED"},
  {"_id":"Seq-2","_barcode":"0033","_name":"Coca-Cola Zero sin cafeina","_description":"","_price":0.6,"_basePrice":0.3,"_stock":10,"_stockMin":100,"_weighted":false,"_categoryId":"3d8dbdcb-fe7a-4e26-baa4-d74f612fe8d4","_status":"PRODUCT_ENABLED"},
  {"_id":"Seq-3","_barcode":"0034","_name":"Coca-Cola Zero zero","_description":"","_price":0.6,"_basePrice":0.3,"_stock":10,"_stockMin":100,"_weighted":false,"_categoryId":"3d8dbdcb-fe7a-4e26-baa4-d74f612fe8d4","_status":"PRODUCT_ENABLED"},
  {"_id":"Seq-4","_barcode":"0035","_name":"Coca-Cola Zero 42","_description":"","_price":0.6,"_basePrice":0.3,"_stock":10,"_stockMin":100,"_weighted":false,"_categoryId":"3d8dbdcb-fe7a-4e26-baa4-d74f612fe8d4","_status":"PRODUCT_ENABLED"},
  {"_id":"Seq-0","_barcode":"0036","_name":"Coca-Cola","_description":"","_price":0.55,"_basePrice":0.3,"_stock":100,"_stockMin":10,"_weighted":false,"_categoryId":"3d8dbdcb-fe7a-4e26-baa4-d74f612fe8d4","_status":"PRODUCT_ENABLED"},
  {"_id":"Seq-1","_barcode":"0037","_name":"Coca-Cola Zero","_description":"","_price":0.6,"_basePrice":0.3,"_stock":1500,"_stockMin":10,"_weighted":false,"_categoryId":"3d8dbdcb-fe7a-4e26-baa4-d74f612fe8d4","_status":"PRODUCT_ENABLED"},
  {"_id":"Seq-2","_barcode":"0038","_name":"Coca-Cola Zero sin cafeina","_description":"","_price":0.6,"_basePrice":0.3,"_stock":10,"_stockMin":100,"_weighted":false,"_categoryId":"3d8dbdcb-fe7a-4e26-baa4-d74f612fe8d4","_status":"PRODUCT_ENABLED"},
  {"_id":"Seq-3","_barcode":"0039","_name":"Coca-Cola Zero zero","_description":"","_price":0.6,"_basePrice":0.3,"_stock":10,"_stockMin":100,"_weighted":false,"_categoryId":"3d8dbdcb-fe7a-4e26-baa4-d74f612fe8d4","_status":"PRODUCT_ENABLED"},
  {"_id":"Seq-4","_barcode":"0040","_name":"Coca-Cola Zero 42","_description":"","_price":0.6,"_basePrice":0.3,"_stock":10,"_stockMin":100,"_weighted":false,"_categoryId":"3d8dbdcb-fe7a-4e26-baa4-d74f612fe8d4","_status":"PRODUCT_ENABLED"},
  {"_id":"Seq-2","_barcode":"0041","_name":"Coca-Cola Zero sin cafeina","_description":"","_price":0.6,"_basePrice":0.3,"_stock":10,"_stockMin":100,"_weighted":false,"_categoryId":"3d8dbdcb-fe7a-4e26-baa4-d74f612fe8d4","_status":"PRODUCT_ENABLED"},
  {"_id":"Seq-3","_barcode":"0042","_name":"Coca-Cola Zero lowStock","_description":"","_price":0.6,"_basePrice":0.3,"_stock":10,"_stockMin":100,"_weighted":false,"_categoryId":"3d8dbdcb-fe7a-4e26-baa4-d74f612fe8d4","_status":"PRODUCT_ENABLED"},
  {"_id":"Seq-4","_barcode":"0043","_name":"Coca-Cola Zero lowStock 42","_description":"","_price":0.6,"_basePrice":0.3,"_stock":10,"_stockMin":100,"_weighted":false,"_categoryId":"3d8dbdcb-fe7a-4e26-baa4-d74f612fe8d4","_status":"PRODUCT_ENABLED"}
]
